LICENSE
nameko_reloader/__init__.py
nameko_reloader/cli_commands.py
nameko_reloader/nameko_reloader.py
nameko_reloader-0.2.0.dist-info/LICENSE
nameko_reloader-0.2.0.dist-info/METADATA
nameko_reloader-0.2.0.dist-info/WHEEL
nameko_reloader-0.2.0.dist-info/entry_points.txt
nameko_reloader-0.2.0.dist-info/RECORD
