Metadata-Version: 2.1
Name: nameko-reloader
Version: 0.2.0
Summary: Add hot reload feature for nameko services
Home-page: https://github.com/instruct-br/nameko-reloader
License: MIT
Keywords: nameko,hot,reload
Author: Instruct Developers
Author-email: oss@instruct.com.br
Requires-Python: >=3.9,<4.0
Classifier: License :: OSI Approved :: MIT License
Classifier: Operating System :: OS Independent
Classifier: Programming Language :: Python :: 3
Classifier: Programming Language :: Python :: 3.9
Classifier: Programming Language :: Python :: 3.10
Classifier: Programming Language :: Python :: 3.11
Requires-Dist: nameko (>=2.14,<2.15)
Project-URL: Repository, https://github.com/instruct-br/nameko-reloader
